rctoolf/__init__.py
rctoolf/webhook.py
rctoolf-0.0.4.dist-info/LICENSE
rctoolf-0.0.4.dist-info/METADATA
rctoolf-0.0.4.dist-info/WHEEL
rctoolf-0.0.4.dist-info/top_level.txt
rctoolf-0.0.4.dist-info/RECORD
