Metadata-Version: 2.1
Name: rctoolf
Version: 0.0.4
Summary: Tools for RC
Author-email: Glorin Li <ligr1991@gmail.com>
License: MIT License
Project-URL: Homepage, https://github.com/glorinli/rctoolf
Keywords: rc,webhook
Classifier: License :: OSI Approved :: MIT License
Classifier: Programming Language :: Python
Classifier: Programming Language :: Python :: 3
Requires-Python: >=3.0
License-File: LICENSE
